flask_autofixture
