Metadata-Version: 1.1
Name: Flask-AutoFixture
Version: 0.2.3
Summary: Flask extension for recording JSON fixtures right from your test suite
Home-page: https://github.com/janukobytsch/flask-autofixture
Author: Janusch Jacoby
Author-email: janusch.jacoby@web.de
License: MIT License
Platform: any
Classifier: Development Status :: 4 - Beta
Classifier: Intended Audience :: Developers
Classifier: License :: OSI Approved :: MIT License
Classifier: Operating System :: OS Independent
Classifier: Programming Language :: Python
Classifier: Programming Language :: Python :: 3
Classifier: Topic :: Internet :: WWW/HTTP :: Dynamic Content
Classifier: Topic :: Software Development :: Libraries :: Python Modules
